{
  "main": {
    "id": "4041213c5c5283d7",
    "type": "split",
    "children": [
      {
        "id": "110f50c6b8983a27",
        "type": "tabs",
        "children": [
          {
            "id": "4dbee3be406ca553",
            "type": "leaf",
            "state": {
              "type": "markdown",
              "state": {
                "file": "03 Betrieb/Log.md",
                "mode": "source",
                "source": false
              },
              "icon": "lucide-file",
              "title": "Log"
            }
          }
        ]
      }
    ],
    "direction": "vertical"
  },
  "left": {
    "id": "d16037e7f8012d17",
    "type": "split",
    "children": [
      {
        "id": "6f19c60eb59de729",
        "type": "tabs",
        "children": [
          {
            "id": "70f2608e7b50c4a5",
            "type": "leaf",
            "state": {
              "type": "file-explorer",
              "state": {
                "sortOrder": "alphabetical",
                "autoReveal": false
              },
              "icon": "lucide-folder-closed",
              "title": "Dateiexplorer"
            }
          },
          {
            "id": "3a7a40e154f5dc5c",
            "type": "leaf",
            "state": {
              "type": "search",
              "state": {
                "query": "",
                "matchingCase": false,
                "explainSearch": false,
                "collapseAll": false,
                "extraContext": false,
                "sortOrder": "alphabetical"
              },
              "icon": "lucide-search",
              "title": "Suchen"
            }
          },
          {
            "id": "b6fa53601df60674",
            "type": "leaf",
            "state": {
              "type": "bookmarks",
              "state": {},
              "icon": "lucide-bookmark",
              "title": "Lesezeichen"
            }
          }
        ]
      }
    ],
    "direction": "horizontal",
    "width": 300
  },
  "right": {
    "id": "5a17f4c9a1be4288",
    "type": "split",
    "children": [
      {
        "id": "d9abf8bda1aa9d07",
        "type": "tabs",
        "children": [
          {
            "id": "471142ab7f540938",
            "type": "leaf",
            "state": {
              "type": "backlink",
              "state": {
                "file": "03 Betrieb/Log.md",
                "collapseAll": false,
                "extraContext": false,
                "sortOrder": "alphabetical",
                "showSearch": false,
                "searchQuery": "",
                "backlinkCollapsed": false,
                "unlinkedCollapsed": true
              },
              "icon": "links-coming-in",
              "title": "Rückverweise auf Log"
            }
          },
          {
            "id": "7e6d3fa8358f25da",
            "type": "leaf",
            "state": {
              "type": "outgoing-link",
              "state": {
                "file": "03 Betrieb/Log.md",
                "linksCollapsed": false,
                "unlinkedCollapsed": true
              },
              "icon": "links-going-out",
              "title": "Ausgehende Links von Log öffnen"
            }
          },
          {
            "id": "a947341e1b706d2b",
            "type": "leaf",
            "state": {
              "type": "tag",
              "state": {
                "sortOrder": "frequency",
                "useHierarchy": true,
                "showSearch": false,
                "searchQuery": ""
              },
              "icon": "lucide-tags",
              "title": "Tags"
            }
          },
          {
            "id": "42e20d4f042dafda",
            "type": "leaf",
            "state": {
              "type": "all-properties",
              "state": {
                "sortOrder": "frequency",
                "showSearch": false,
                "searchQuery": ""
              },
              "icon": "lucide-archive",
              "title": "Alle Eigenschaften"
            }
          },
          {
            "id": "20e1f2567f1ba406",
            "type": "leaf",
            "state": {
              "type": "outline",
              "state": {
                "file": "03 Betrieb/Log.md",
                "followCursor": false,
                "showSearch": false,
                "searchQuery": ""
              },
              "icon": "lucide-list",
              "title": "Gliederung von Log"
            }
          }
        ]
      }
    ],
    "direction": "horizontal",
    "width": 300,
    "collapsed": true
  },
  "left-ribbon": {
    "hiddenItems": {
      "switcher:Schnellauswahl öffnen": false,
      "graph:Graph-Ansicht öffnen": false,
      "canvas:Neuen Canvas erstellen": false,
      "daily-notes:Heutige Notiz öffnen": false,
      "templates:Vorlage einfügen": false,
      "command-palette:Befehlspalette öffnen": false,
      "bases:Neue Base erstellen": false
    }
  },
  "active": "4dbee3be406ca553",
  "lastOpenFiles": [
    "02 Wissen/Prozesse/Debug Studio-Statistik und 10-Studio-Report 2026-04-20.md",
    "02 Wissen/Prozesse/Einordnung PHP CodeSniffer fuer dieses Projekt 2026-04-20.md",
    "01 Rohquellen/web/PHP_CodeSniffer Referenz 2026-04-20.md",
    "01 Rohquellen/web",
    "02 Wissen/00 Uebersichten/Aktueller Projektstatus.md",
    "02 Wissen/Prozesse/Wiki-first Query und Linting.md",
    "02 Wissen/Prozesse/Bewertung Tests 11 bis 20 E2E-App-Spec 2026-04-20.md",
    "02 Wissen/Prozesse/Bewertung erste 10 E2E-Startflow-Tests 2026-04-20.md",
    "02 Wissen/Prozesse/Arbeitsworkflow Wissenspflege und Projektanfragen.md"
  ]
}